azure/mgmt/networkfunction/__init__.py
azure/mgmt/networkfunction/_configuration.py
azure/mgmt/networkfunction/_patch.py
azure/mgmt/networkfunction/_serialization.py
azure/mgmt/networkfunction/_traffic_collector_mgmt_client.py
azure/mgmt/networkfunction/_vendor.py
azure/mgmt/networkfunction/_version.py
azure/mgmt/networkfunction/py.typed
azure/mgmt/networkfunction/aio/__init__.py
azure/mgmt/networkfunction/aio/_configuration.py
azure/mgmt/networkfunction/aio/_patch.py
azure/mgmt/networkfunction/aio/_traffic_collector_mgmt_client.py
azure/mgmt/networkfunction/aio/operations/__init__.py
azure/mgmt/networkfunction/aio/operations/_azure_traffic_collectors_by_resource_group_operations.py
azure/mgmt/networkfunction/aio/operations/_azure_traffic_collectors_by_subscription_operations.py
azure/mgmt/networkfunction/aio/operations/_azure_traffic_collectors_operations.py
azure/mgmt/networkfunction/aio/operations/_collector_policies_operations.py
azure/mgmt/networkfunction/aio/operations/_network_function_operations.py
azure/mgmt/networkfunction/aio/operations/_patch.py
azure/mgmt/networkfunction/models/__init__.py
azure/mgmt/networkfunction/models/_models_py3.py
azure/mgmt/networkfunction/models/_patch.py
azure/mgmt/networkfunction/models/_traffic_collector_mgmt_client_enums.py
azure/mgmt/networkfunction/operations/__init__.py
azure/mgmt/networkfunction/operations/_azure_traffic_collectors_by_resource_group_operations.py
azure/mgmt/networkfunction/operations/_azure_traffic_collectors_by_subscription_operations.py
azure/mgmt/networkfunction/operations/_azure_traffic_collectors_operations.py
azure/mgmt/networkfunction/operations/_collector_policies_operations.py
azure/mgmt/networkfunction/operations/_network_function_operations.py
azure/mgmt/networkfunction/operations/_patch.py
azure_mgmt_networkfunction-1.0.0b1.dist-info/LICENSE
azure_mgmt_networkfunction-1.0.0b1.dist-info/METADATA
azure_mgmt_networkfunction-1.0.0b1.dist-info/WHEEL
azure_mgmt_networkfunction-1.0.0b1.dist-info/top_level.txt
azure_mgmt_networkfunction-1.0.0b1.dist-info/RECORD
